RPiParticle-0.9.3.data/data/bin/fby_controlpanel
RPiParticle-0.9.3.data/data/bin/fby_manager
RPiParticle-0.9.3.data/data/bin/fby_sampler
RPiParticle-0.9.3.data/data/bin/fby_submitter
RPiParticle-0.9.3.data/data/lib/systemd/system/friskby-controlpanel.service
RPiParticle-0.9.3.data/data/lib/systemd/system/friskby-sampler.service
RPiParticle-0.9.3.data/data/lib/systemd/system/friskby-submitter.service
RPiParticle-0.9.3.data/data/lib/systemd/system/friskby.service
RPiParticle-0.9.3.dist-info/DESCRIPTION.rst
RPiParticle-0.9.3.dist-info/METADATA
RPiParticle-0.9.3.dist-info/RECORD
RPiParticle-0.9.3.dist-info/WHEEL
RPiParticle-0.9.3.dist-info/metadata.json
RPiParticle-0.9.3.dist-info/top_level.txt
rpiparticle/__init__.py
rpiparticle/fby_settings.py
rpiparticle/friskby-settings.json
