Metadata-Version: 2.0
Name: RPiParticle
Version: 0.9.3
Summary: Raspberry Pi and SDS011 particle sensor posting data 
Home-page: https://github.com/FriskByBergen/
Author: Friskby Bergen
Author-email: jonas@drange.net
License: GNU General Public License, Version 3
Platform: UNKNOWN
Classifier: Development Status :: 3 - Alpha
Classifier: Intended Audience :: Developers
Classifier: Topic :: Software Development :: Build Tools
Classifier: License :: OSI Approved :: GNU General Public License v3 or later (GPLv3+)
Classifier: Programming Language :: Python :: 2.7
Requires-Dist: requests
Requires-Dist: pyserial
Requires-Dist: python-dateutil
Requires-Dist: friskby (>=0.66)
Requires-Dist: friskby-controlpanel
